[
  {
    "year": 2005,
    "state": "Tamil Nadu",
    "district": "Chennai",
    "gender": "Male",
    "applied": 2500,
    "worked": 2100,
    "not_worked": 400,
    "days_worked": 85,
    "wage_rate": 120,
    "total_wages": 21420000
  },
  {
    "year": 2005,
    "state": "Tamil Nadu",
    "district": "Chennai",
    "gender": "Female",
    "applied": 1800,
    "worked": 1500,
    "not_worked": 300,
    "days_worked": 82,
    "wage_rate": 120,
    "total_wages": 14760000
  },
  {
    "year": 2005,
    "state": "Tamil Nadu",
    "district": "Coimbatore",
    "gender": "Male",
    "applied": 3200,
    "worked": 2800,
    "not_worked": 400,
    "days_worked": 88,
    "wage_rate": 115,
    "total_wages": 28336000
  },
  {
    "year": 2005,
    "state": "Tamil Nadu",
    "district": "Coimbatore",
    "gender": "Female",
    "applied": 2400,
    "worked": 2100,
    "not_worked": 300,
    "days_worked": 85,
    "wage_rate": 115,
    "total_wages": 20527500
  },
  {
    "year": 2005,
    "state": "Tamil Nadu",
    "district": "Madurai",
    "gender": "Male",
    "applied": 4500,
    "worked": 3900,
    "not_worked": 600,
    "days_worked": 92,
    "wage_rate": 110,
    "total_wages": 39468000
  },
  {
    "year": 2005,
    "state": "Tamil Nadu",
    "district": "Madurai",
    "gender": "Female",
    "applied": 3800,
    "worked": 3300,
    "not_worked": 500,
    "days_worked": 89,
    "wage_rate": 110,
    "total_wages": 32307000
  },
  {
    "year": 2005,
    "state": "Tamil Nadu",
    "district": "Tiruchirappalli",
    "gender": "Male",
    "applied": 3800,
    "worked": 3200,
    "not_worked": 600,
    "days_worked": 87,
    "wage_rate": 112,
    "total_wages": 31116800
  },
  {
    "year": 2005,
    "state": "Tamil Nadu",
    "district": "Tiruchirappalli",
    "gender": "Female",
    "applied": 3200,
    "worked": 2800,
    "not_worked": 400,
    "days_worked": 84,
    "wage_rate": 112,
    "total_wages": 26316800
  },
  {
    "year": 2005,
    "state": "Tamil Nadu",
    "district": "Salem",
    "gender": "Male",
    "applied": 4200,
    "worked": 3600,
    "not_worked": 600,
    "days_worked": 90,
    "wage_rate": 108,
    "total_wages": 34992000
  },
  {
    "year": 2005,
    "state": "Tamil Nadu",
    "district": "Salem",
    "gender": "Female",
    "applied": 3500,
    "worked": 3000,
    "not_worked": 500,
    "days_worked": 87,
    "wage_rate": 108,
    "total_wages": 28242000
  },
  {
    "year": 2005,
    "state": "Tamil Nadu",
    "district": "Tirunelveli",
    "gender": "Male",
    "applied": 5200,
    "worked": 4500,
    "not_worked": 700,
    "days_worked": 95,
    "wage_rate": 105,
    "total_wages": 44887500
  },
  {
    "year": 2005,
    "state": "Tamil Nadu",
    "district": "Tirunelveli",
    "gender": "Female",
    "applied": 4800,
    "worked": 4200,
    "not_worked": 600,
    "days_worked": 92,
    "wage_rate": 105,
    "total_wages": 40572000
  },
  {
    "year": 2005,
    "state": "Tamil Nadu",
    "district": "Vellore",
    "gender": "Male",
    "applied": 3600,
    "worked": 3100,
    "not_worked": 500,
    "days_worked": 86,
    "wage_rate": 110,
    "total_wages": 29326000
  },
  {
    "year": 2005,
    "state": "Tamil Nadu",
    "district": "Vellore",
    "gender": "Female",
    "applied": 2900,
    "worked": 2500,
    "not_worked": 400,
    "days_worked": 83,
    "wage_rate": 110,
    "total_wages": 22825000
  },
  {
    "year": 2005,
    "state": "Tamil Nadu",
    "district": "Erode",
    "gender": "Male",
    "applied": 3400,
    "worked": 2900,
    "not_worked": 500,
    "days_worked": 88,
    "wage_rate": 108,
    "total_wages": 27561600
  },
  {
    "year": 2005,
    "state": "Tamil Nadu",
    "district": "Erode",
    "gender": "Female",
    "applied": 2800,
    "worked": 2400,
    "not_worked": 400,
    "days_worked": 85,
    "wage_rate": 108,
    "total_wages": 22032000
  },
  {
    "year": 2005,
    "state": "Tamil Nadu",
    "district": "Tirupur",
    "gender": "Male",
    "applied": 2800,
    "worked": 2400,
    "not_worked": 400,
    "days_worked": 82,
    "wage_rate": 115,
    "total_wages": 22632000
  },
  {
    "year": 2005,
    "state": "Tamil Nadu",
    "district": "Tirupur",
    "gender": "Female",
    "applied": 2200,
    "worked": 1900,
    "not_worked": 300,
    "days_worked": 79,
    "wage_rate": 115,
    "total_wages": 17253500
  },
  {
    "year": 2005,
    "state": "Tamil Nadu",
    "district": "Dindigul",
    "gender": "Male",
    "applied": 4100,
    "worked": 3500,
    "not_worked": 600,
    "days_worked": 91,
    "wage_rate": 107,
    "total_wages": 34072500
  },
  {
    "year": 2005,
    "state": "Tamil Nadu",
    "district": "Dindigul",
    "gender": "Female",
    "applied": 3400,
    "worked": 2900,
    "not_worked": 500,
    "days_worked": 88,
    "wage_rate": 107,
    "total_wages": 27313200
  },
  {
    "year": 2005,
    "state": "Tamil Nadu",
    "district": "Thanjavur",
    "gender": "Male",
    "applied": 4800,
    "worked": 4200,
    "not_worked": 600,
    "days_worked": 94,
    "wage_rate": 109,
    "total_wages": 43077600
  },
  {
    "year": 2005,
    "state": "Tamil Nadu",
    "district": "Thanjavur",
    "gender": "Female",
    "applied": 4200,
    "worked": 3700,
    "not_worked": 500,
    "days_worked": 91,
    "wage_rate": 109,
    "total_wages": 36703700
  },
  {
    "year": 2005,
    "state": "Tamil Nadu",
    "district": "Nagapattinam",
    "gender": "Male",
    "applied": 3200,
    "worked": 2800,
    "not_worked": 400,
    "days_worked": 89,
    "wage_rate": 108,
    "total_wages": 26899200
  },
  {
    "year": 2005,
    "state": "Tamil Nadu",
    "district": "Nagapattinam",
    "gender": "Female",
    "applied": 2800,
    "worked": 2400,
    "not_worked": 400,
    "days_worked": 86,
    "wage_rate": 108,
    "total_wages": 22291200
  },
  {
    "year": 2005,
    "state": "Tamil Nadu",
    "district": "Cuddalore",
    "gender": "Male",
    "applied": 3800,
    "worked": 3300,
    "not_worked": 500,
    "days_worked": 87,
    "wage_rate": 111,
    "total_wages": 31878900
  },
  {
    "year": 2005,
    "state": "Tamil Nadu",
    "district": "Cuddalore",
    "gender": "Female",
    "applied": 3200,
    "worked": 2800,
    "not_worked": 400,
    "days_worked": 84,
    "wage_rate": 111,
    "total_wages": 26150400
  },
  {
    "year": 2005,
    "state": "Tamil Nadu",
    "district": "Villupuram",
    "gender": "Male",
    "applied": 4500,
    "worked": 3900,
    "not_worked": 600,
    "days_worked": 92,
    "wage_rate": 106,
    "total_wages": 38044800
  },
  {
    "year": 2005,
    "state": "Tamil Nadu",
    "district": "Villupuram",
    "gender": "Female",
    "applied": 3800,
    "worked": 3300,
    "not_worked": 500,
    "days_worked": 89,
    "wage_rate": 106,
    "total_wages": 31137400
  },
  {
    "year": 2005,
    "state": "Tamil Nadu",
    "district": "Kanchipuram",
    "gender": "Male",
    "applied": 2900,
    "worked": 2500,
    "not_worked": 400,
    "days_worked": 83,
    "wage_rate": 118,
    "total_wages": 24485000
  },
  {
    "year": 2005,
    "state": "Tamil Nadu",
    "district": "Kanchipuram",
    "gender": "Female",
    "applied": 2400,
    "worked": 2100,
    "not_worked": 300,
    "days_worked": 80,
    "wage_rate": 118,
    "total_wages": 19824000
  },
  {
    "year": 2005,
    "state": "Tamil Nadu",
    "district": "Tiruvallur",
    "gender": "Male",
    "applied": 3100,
    "worked": 2700,
    "not_worked": 400,
    "days_worked": 85,
    "wage_rate": 116,
    "total_wages": 26622000
  },
  {
    "year": 2005,
    "state": "Tamil Nadu",
    "district": "Tiruvallur",
    "gender": "Female",
    "applied": 2600,
    "worked": 2200,
    "not_worked": 400,
    "days_worked": 82,
    "wage_rate": 116,
    "total_wages": 20950400
  },
  {
    "year": 2010,
    "state": "Tamil Nadu",
    "district": "Chennai",
    "gender": "Male",
    "applied": 3200,
    "worked": 2800,
    "not_worked": 400,
    "days_worked": 88,
    "wage_rate": 145,
    "total_wages": 35784000
  },
  {
    "year": 2010,
    "state": "Tamil Nadu",
    "district": "Chennai",
    "gender": "Female",
    "applied": 2400,
    "worked": 2100,
    "not_worked": 300,
    "days_worked": 85,
    "wage_rate": 145,
    "total_wages": 25882500
  },
  {
    "year": 2010,
    "state": "Tamil Nadu",
    "district": "Coimbatore",
    "gender": "Male",
    "applied": 4100,
    "worked": 3600,
    "not_worked": 500,
    "days_worked": 91,
    "wage_rate": 140,
    "total_wages": 45864000
  },
  {
    "year": 2010,
    "state": "Tamil Nadu",
    "district": "Coimbatore",
    "gender": "Female",
    "applied": 3200,
    "worked": 2800,
    "not_worked": 400,
    "days_worked": 88,
    "wage_rate": 140,
    "total_wages": 34496000
  },
  {
    "year": 2010,
    "state": "Tamil Nadu",
    "district": "Madurai",
    "gender": "Male",
    "applied": 5800,
    "worked": 5100,
    "not_worked": 700,
    "days_worked": 95,
    "wage_rate": 135,
    "total_wages": 65407500
  },
  {
    "year": 2010,
    "state": "Tamil Nadu",
    "district": "Madurai",
    "gender": "Female",
    "applied": 4900,
    "worked": 4300,
    "not_worked": 600,
    "days_worked": 92,
    "wage_rate": 135,
    "total_wages": 53406000
  },
  {
    "year": 2015,
    "state": "Tamil Nadu",
    "district": "Chennai",
    "gender": "Male",
    "applied": 4200,
    "worked": 3800,
    "not_worked": 400,
    "days_worked": 92,
    "wage_rate": 168,
    "total_wages": 58761600
  },
  {
    "year": 2015,
    "state": "Tamil Nadu",
    "district": "Chennai",
    "gender": "Female",
    "applied": 3400,
    "worked": 3100,
    "not_worked": 300,
    "days_worked": 89,
    "wage_rate": 168,
    "total_wages": 46315200
  },
  {
    "year": 2015,
    "state": "Tamil Nadu",
    "district": "Coimbatore",
    "gender": "Male",
    "applied": 5400,
    "worked": 4900,
    "not_worked": 500,
    "days_worked": 94,
    "wage_rate": 162,
    "total_wages": 74548800
  },
  {
    "year": 2015,
    "state": "Tamil Nadu",
    "district": "Coimbatore",
    "gender": "Female",
    "applied": 4300,
    "worked": 3900,
    "not_worked": 400,
    "days_worked": 91,
    "wage_rate": 162,
    "total_wages": 57477000
  },
  {
    "year": 2020,
    "state": "Tamil Nadu",
    "district": "Chennai",
    "gender": "Male",
    "applied": 5800,
    "worked": 5400,
    "not_worked": 400,
    "days_worked": 96,
    "wage_rate": 202,
    "total_wages": 104832000
  },
  {
    "year": 2020,
    "state": "Tamil Nadu",
    "district": "Chennai",
    "gender": "Female",
    "applied": 4900,
    "worked": 4600,
    "not_worked": 300,
    "days_worked": 93,
    "wage_rate": 202,
    "total_wages": 86347600
  },
  {
    "year": 2020,
    "state": "Tamil Nadu",
    "district": "Coimbatore",
    "gender": "Male",
    "applied": 7200,
    "worked": 6800,
    "not_worked": 400,
    "days_worked": 97,
    "wage_rate": 195,
    "total_wages": 128556000
  },
  {
    "year": 2020,
    "state": "Tamil Nadu",
    "district": "Coimbatore",
    "gender": "Female",
    "applied": 5800,
    "worked": 5500,
    "not_worked": 300,
    "days_worked": 94,
    "wage_rate": 195,
    "total_wages": 100815000
  },
  {
    "year": 2023,
    "state": "Tamil Nadu",
    "district": "Chennai",
    "gender": "Male",
    "applied": 6800,
    "worked": 6500,
    "not_worked": 300,
    "days_worked": 98,
    "wage_rate": 256,
    "total_wages": 163072000
  },
  {
    "year": 2023,
    "state": "Tamil Nadu",
    "district": "Chennai",
    "gender": "Female",
    "applied": 5900,
    "worked": 5700,
    "not_worked": 200,
    "days_worked": 95,
    "wage_rate": 256,
    "total_wages": 138624000
  },
  {
    "year": 2024,
    "state": "Tamil Nadu",
    "district": "Chennai",
    "gender": "Male",
    "applied": 7200,
    "worked": 6950,
    "not_worked": 250,
    "days_worked": 99,
    "wage_rate": 275,
    "total_wages": 189481250
  },
  {
    "year": 2024,
    "state": "Tamil Nadu",
    "district": "Chennai",
    "gender": "Female",
    "applied": 6200,
    "worked": 6000,
    "not_worked": 200,
    "days_worked": 96,
    "wage_rate": 275,
    "total_wages": 158400000
  }
]
